mooon/__init__.py
mooon/functional.py
mooon/layers.py
mooon/version.py
mooon-0.0.1b0.dist-info/LICENSE
mooon-0.0.1b0.dist-info/METADATA
mooon-0.0.1b0.dist-info/WHEEL
mooon-0.0.1b0.dist-info/top_level.txt
mooon-0.0.1b0.dist-info/RECORD
