Metadata-Version: 2.1
Name: mooon
Version: 0.0.1b0
Summary: Graph data augmentation library
Home-page: https://github.com/EdisonLeeeee/Mooon
Download-URL: https://github.com/EdisonLeeeee/Mooon/archive/0.0.1b0.tar.gz
Author: Jintang Li
Author-email: lijt55@mail2.sysu.edu.cn
License: MIT LICENSE
Keywords: torch_geometric,pytorch,benchmark,geometric-adversarial-learning,graph-neural-networks,graph-data-augmentation
Classifier: Development Status :: 3 - Alpha
Classifier: Intended Audience :: Science/Research
Classifier: License :: OSI Approved :: MIT License
Classifier: Topic :: Scientific/Engineering :: Artificial Intelligence
Classifier: Topic :: Scientific/Engineering
Classifier: Topic :: Software Development :: Libraries
Classifier: Operating System :: Microsoft :: Windows
Classifier: Operating System :: Unix
Classifier: Programming Language :: Python :: 3
Classifier: Programming Language :: Python :: 3.7
Classifier: Programming Language :: Python :: 3.8
Requires-Python: >=3.7
License-File: LICENSE
Requires-Dist: tqdm
Requires-Dist: scipy
Requires-Dist: numpy
Requires-Dist: tabulate
Requires-Dist: pandas
Requires-Dist: termcolor
Requires-Dist: scikit-learn
Requires-Dist: matplotlib
Provides-Extra: dev
Requires-Dist: pytest ; extra == 'dev'
Requires-Dist: pytest-cov ; extra == 'dev'
Requires-Dist: pre-commit ; extra == 'dev'
Provides-Extra: full
Requires-Dist: numba ; extra == 'full'
Requires-Dist: pandas ; extra == 'full'
Requires-Dist: matplotlib ; extra == 'full'
Requires-Dist: networkx (>=2.3) ; extra == 'full'
Provides-Extra: test
Requires-Dist: pytest ; extra == 'test'
Requires-Dist: pytest-cov ; extra == 'test'
